domonic/CDN.py
domonic/JSON.py
domonic/__init__.py
domonic/__main__.py
domonic/cmd.py
domonic/components.py
domonic/dQuery.py
domonic/decorators.py
domonic/dom.py
domonic/events.py
domonic/html.py
domonic/javascript.py
domonic/style.py
domonic/svg.py
domonic/terminal.py
domonic/utils.py
domonic/window.py
domonic/constants/__init__.py
domonic/constants/color.py
domonic/constants/entities.py
domonic/constants/keyboard.py
domonic/d3/__init__.py
domonic/d3/dispatch.py
domonic/d3/format.py
domonic/d3/path.py
domonic/d3/polygon.py
domonic/d3/queue.py
domonic/d3/selection.py
domonic/d3/tile.py
domonic/d3/timer.py
domonic/ext/__init__.py
domonic/ext/sseclient.py
domonic/ext/html5_parser_/__init__.py
domonic/ext/html5_parser_/dom.py
domonic/ext/html5lib_/__init__.py
domonic/game/__init__.py
domonic/geom/__init__.py
domonic/geom/particles.py
domonic/geom/vec2.py
domonic/geom/vec3.py
domonic/geom/vec4.py
domonic/geom/shape/__init__.py
domonic/geom/shape/shapes.py
domonic/i18n/__init__.py
domonic/i18n/ar/__init__.py
domonic/i18n/ch/__init__.py
domonic/i18n/da/__init__.py
domonic/i18n/de/__init__.py
domonic/i18n/es/__init__.py
domonic/i18n/fr/__init__.py
domonic/i18n/hi/__init__.py
domonic/i18n/it/__init__.py
domonic/i18n/mi/__init__.py
domonic/i18n/ru/__init__.py
domonic/i18n/sw/__init__.py
domonic/i18n/uk/__init__.py
domonic/i18n/zu/__init__.py
domonic/lerpy/__init__.py
domonic/lerpy/easing.py
domonic/lerpy/tween.py
domonic/parsers/__init__.py
domonic/parsers/expatbuilder.py
domonic/tags/__init__.py
domonic/templates/__init__.py
domonic/webapi/__init__.py
domonic/webapi/clipboard.py
domonic/webapi/console.py
domonic/webapi/credentials.py
domonic/webapi/dragndrop.py
domonic/webapi/encoding.py
domonic/webapi/fetch.py
domonic/webapi/geo.py
domonic/webapi/history.py
domonic/webapi/mediacapabilities.py
domonic/webapi/mediadevices.py
domonic/webapi/mediasession.py
domonic/webapi/messaging.py
domonic/webapi/netinfo.py
domonic/webapi/permissions.py
domonic/webapi/push.py
domonic-0.9.13.dist-info/LICENSE.txt
domonic-0.9.13.dist-info/METADATA
domonic-0.9.13.dist-info/WHEEL
domonic-0.9.13.dist-info/entry_points.txt
domonic-0.9.13.dist-info/top_level.txt
domonic-0.9.13.dist-info/RECORD
