Metadata-Version: 2.1
Name: domonic
Version: 0.9.13
Summary: Generate html with python 3. DOM API, Javascript API and more...
Home-page: https://github.com/byteface/domonic
Author: @byteface
Author-email: byteface@gmail.com
License: MIT
Download-URL: https://github.com/byteface/domonic/archive/0.9.13.tar.gz
Keywords: html,generate,templating,dom,vdom,terminal,json,web,template,javascript,DOM,GUI,render,website,apps,html5,framework,SVG,x3d,events,geom
Platform: UNKNOWN
Classifier: Programming Language :: Python :: 3
Classifier: Programming Language :: JavaScript
Classifier: Programming Language :: Python
Classifier: Programming Language :: Python :: 3.7
Classifier: Programming Language :: Python :: 3.8
Classifier: Programming Language :: Python :: 3.9
Classifier: Programming Language :: Python :: 3.10
Classifier: Programming Language :: Python :: 3.11
Classifier: Programming Language :: Python :: 3.12
Classifier: Development Status :: 4 - Beta
Classifier: Environment :: Web Environment
Classifier: Intended Audience :: Developers
Classifier: Intended Audience :: Other Audience
Classifier: License :: OSI Approved :: MIT License
Classifier: Natural Language :: English
Classifier: Operating System :: OS Independent
Classifier: Topic :: Internet
Classifier: Topic :: Internet :: WWW/HTTP
Classifier: Topic :: Multimedia :: Graphics :: Presentation
Classifier: Topic :: Software Development
Classifier: Topic :: Software Development :: Code Generators
Classifier: Topic :: Terminals
Classifier: Topic :: Utilities
Classifier: Topic :: Internet :: WWW/HTTP :: Dynamic Content
Classifier: Topic :: Software Development :: Libraries :: Python Modules
Classifier: Topic :: Text Processing :: Markup :: HTML
Requires-Python: >=3.6
License-File: LICENSE.txt
Requires-Dist: elementpath~=4.6.0
Requires-Dist: python-dateutil==2.9.0.post0
Requires-Dist: requests~=2.32.3
Requires-Dist: urllib3~=2.2.3
Requires-Dist: html5lib~=1.1
Requires-Dist: cssselect~=1.2.0
